djangocms_snippet/__init__.py
djangocms_snippet/admin.py
djangocms_snippet/apps.py
djangocms_snippet/cms_config.py
djangocms_snippet/cms_plugins.py
djangocms_snippet/conf.py
djangocms_snippet/forms.py
djangocms_snippet/models.py
djangocms_snippet/rendering.py
djangocms_snippet/settings.py
djangocms_snippet/utils.py
djangocms_snippet/locale/af/LC_MESSAGES/django.mo
djangocms_snippet/locale/af/LC_MESSAGES/django.po
djangocms_snippet/locale/ar/LC_MESSAGES/django.mo
djangocms_snippet/locale/ar/LC_MESSAGES/django.po
djangocms_snippet/locale/be/LC_MESSAGES/django.mo
djangocms_snippet/locale/be/LC_MESSAGES/django.po
djangocms_snippet/locale/bg/LC_MESSAGES/django.mo
djangocms_snippet/locale/bg/LC_MESSAGES/django.po
djangocms_snippet/locale/bn/LC_MESSAGES/django.mo
djangocms_snippet/locale/bn/LC_MESSAGES/django.po
djangocms_snippet/locale/ca/LC_MESSAGES/django.mo
djangocms_snippet/locale/ca/LC_MESSAGES/django.po
djangocms_snippet/locale/cmn/LC_MESSAGES/django.mo
djangocms_snippet/locale/cmn/LC_MESSAGES/django.po
djangocms_snippet/locale/cs/LC_MESSAGES/django.mo
djangocms_snippet/locale/cs/LC_MESSAGES/django.po
djangocms_snippet/locale/cy/LC_MESSAGES/django.mo
djangocms_snippet/locale/cy/LC_MESSAGES/django.po
djangocms_snippet/locale/da/LC_MESSAGES/django.mo
djangocms_snippet/locale/da/LC_MESSAGES/django.po
djangocms_snippet/locale/de/LC_MESSAGES/django.mo
djangocms_snippet/locale/de/LC_MESSAGES/django.po
djangocms_snippet/locale/el/LC_MESSAGES/django.mo
djangocms_snippet/locale/el/LC_MESSAGES/django.po
djangocms_snippet/locale/en/LC_MESSAGES/django.mo
djangocms_snippet/locale/en/LC_MESSAGES/django.po
djangocms_snippet/locale/es/LC_MESSAGES/django.mo
djangocms_snippet/locale/es/LC_MESSAGES/django.po
djangocms_snippet/locale/es_AR/LC_MESSAGES/django.mo
djangocms_snippet/locale/es_AR/LC_MESSAGES/django.po
djangocms_snippet/locale/es_BO/LC_MESSAGES/django.mo
djangocms_snippet/locale/es_BO/LC_MESSAGES/django.po
djangocms_snippet/locale/es_DO/LC_MESSAGES/django.mo
djangocms_snippet-5.0.2.dist-info/licenses/LICENSE
djangocms_snippet-5.0.2.dist-info/METADATA
djangocms_snippet-5.0.2.dist-info/WHEEL
djangocms_snippet-5.0.2.dist-info/top_level.txt
djangocms_snippet-5.0.2.dist-info/RECORD
