Metadata-Version: 2.4
Name: djangocms-snippet
Version: 5.0.2
Summary: Adds snippet plugin to django CMS.
Author-email: Divio AG <info@divio.ch>
Maintainer-email: Django CMS Association and contributors <info@django-cms.org>
License: Copyright (c) 2011, Divio AG
Project-URL: Bug Tracker, https://github.com/django-cms/djangocms-snippet/issues
Project-URL: Changelog, https://github.com/django-cms/djangocms-snippet/blob/master/CHANGELOG.rst
Project-URL: Repository, https://github.com/django-cms/djangocms-snippet
Project-URL: Support, https://www.django-cms.org/slack/
Classifier: Development Status :: 5 - Production/Stable
Classifier: Environment :: Web Environment
Classifier: Intended Audience :: Developers
Classifier: License :: OSI Approved :: BSD License
Classifier: Operating System :: OS Independent
Classifier: Programming Language :: Python
Classifier: Programming Language :: Python :: 3
Classifier: Programming Language :: Python :: 3.8
Classifier: Programming Language :: Python :: 3.9
Classifier: Programming Language :: Python :: 3.10
Classifier: Framework :: Django
Classifier: Framework :: Django :: 3.2
Classifier: Framework :: Django :: 4.2
Classifier: Framework :: Django CMS
Classifier: Framework :: Django CMS :: 3.8
Classifier: Framework :: Django CMS :: 3.9
Classifier: Framework :: Django CMS :: 3.10
Classifier: Framework :: Django CMS :: 3.11
Classifier: Framework :: Django CMS :: 4.0
Classifier: Framework :: Django CMS :: 4.1
Classifier: Topic :: Internet :: WWW/HTTP
Classifier: Topic :: Internet :: WWW/HTTP :: Dynamic Content
Classifier: Topic :: Software Development
Classifier: Topic :: Software Development :: Libraries
Requires-Python: >=3.9
License-File: LICENSE
Requires-Dist: django-cms>=3.7
Provides-Extra: static-ace
Requires-Dist: djangocms-static-ace; extra == "static-ace"
Dynamic: license-file
